raw_image_converter/__init__.py
raw_image_converter/__main__.py
raw_image_converter/utils.py
raw_image_converter-1.1.3.dist-info/LICENSE
raw_image_converter-1.1.3.dist-info/METADATA
raw_image_converter-1.1.3.dist-info/WHEEL
raw_image_converter-1.1.3.dist-info/entry_points.txt
raw_image_converter-1.1.3.dist-info/RECORD
