Metadata-Version: 2.1
Name: raw-image-converter
Version: 1.1.3
Summary: Batch image convertions
Home-page: https://github.com/achimoraites/Python-Image-Converter
License: MIT
Keywords: cli,converter,raw,images
Author: Achilles Moraites
Author-email: achimoraites@yahoo.gr
Requires-Python: >=3.9,<4.0
Classifier: License :: OSI Approved :: MIT License
Classifier: Programming Language :: Python :: 3
Classifier: Programming Language :: Python :: 3.9
Classifier: Programming Language :: Python :: 3.10
Classifier: Programming Language :: Python :: 3.11
Classifier: Programming Language :: Python :: 3.12
Classifier: Topic :: Utilities
Requires-Dist: colorama (==0.4.6)
Requires-Dist: imageio (==2.16.2)
Requires-Dist: numpy (==1.26.4)
Requires-Dist: pillow (==10.3.0)
Requires-Dist: rawpy (==0.19.1)
Project-URL: Repository, https://github.com/achimoraites/Python-Image-Converter
